selenium_generator/__init__.py
selenium_generator/main.py
selenium_generator/base/__init__.py
selenium_generator/base/exceptions.py
selenium_generator/base/file_manager.py
selenium_generator/base/singleton.py
selenium_generator/factories/__init__.py
selenium_generator/factories/page_factory.py
selenium_generator/factories/drivers/__init__.py
selenium_generator/factories/drivers/base_driver.py
selenium_generator/factories/drivers/driver_factory.py
selenium_generator/factories/drivers/local_driver.py
selenium_generator/factories/drivers/remote_driver.py
selenium_generator/factories/tests/__init__.py
selenium_generator/factories/tests/base_test.py
selenium_generator/factories/tests/test_factory.py
selenium_generator/handlers/__init__.py
selenium_generator/handlers/event_handler.py
selenium_generator/handlers/keywords.py
selenium_generator/parsers/__init__.py
selenium_generator/parsers/arg_parser.py
selenium_generator/parsers/config_parser.py
selenium_generator/test_runner/__init__.py
selenium_generator/test_runner/loader.py
selenium_generator/test_runner/runner.py
selenium_generator/validators/__init__.py
selenium_generator/validators/validator.py
selenium_generator-0.3.dist-info/LICENSE
selenium_generator-0.3.dist-info/METADATA
selenium_generator-0.3.dist-info/WHEEL
selenium_generator-0.3.dist-info/top_level.txt
selenium_generator-0.3.dist-info/RECORD
