Metadata-Version: 2.1
Name: selenium-generator
Version: 0.3
Summary: A framework for automated generating of Selenim WebDriver tests from yaml based on unittest framework.
Home-page: https://github.com/jjaros587/selenium_generator
Author: Jakub Jaroš
Author-email: jjaros587@gmail.com
License: MIT
Keywords: selenium,generator
Platform: any
Requires-Python: >=3.2
Requires-Dist: pyyaml
Requires-Dist: selenium
Requires-Dist: webdriver-manager
Requires-Dist: html-testRunner
Requires-Dist: ddt
Requires-Dist: cerberus
Requires-Dist: sphinx
Requires-Dist: sphinxcontrib-contentui
Provides-Extra: testing
Requires-Dist: unittest ; extra == 'testing'
